wechat_notice.py
wechat_notice-0.0.4.dist-info/LICENSE
wechat_notice-0.0.4.dist-info/METADATA
wechat_notice-0.0.4.dist-info/WHEEL
wechat_notice-0.0.4.dist-info/top_level.txt
wechat_notice-0.0.4.dist-info/RECORD
