Metadata-Version: 2.1
Name: wechat-notice
Version: 0.0.4
Summary: Send Wechat a message at any time.(任何时刻给微信发送消息)
Home-page: https://github.com/sfyc23/wechat_notice
Author: DoubleThunder
Author-email: sfyc23@gmail.com
License: MIT
Keywords: wechat,微信,notice,通知
Platform: UNKNOWN
Classifier: License :: OSI Approved :: MIT License
Classifier: Programming Language :: Python
Classifier: Programming Language :: Python :: 3
Classifier: Programming Language :: Python :: 3.6
Classifier: Programming Language :: Python :: Implementation :: CPython
Classifier: Programming Language :: Python :: Implementation :: PyPy
Requires-Python: >=3.6.0
Requires-Dist: requests
Requires-Dist: yagmail
